osm_rawdata/__version__.py
osm_rawdata/config.py
osm_rawdata/db_models.py
osm_rawdata/db_schemas.py
osm_rawdata/geofabrik.py
osm_rawdata/geofabrik.yaml
osm_rawdata/import/README.md
osm_rawdata/import/nodes.sql
osm_rawdata/import/raw.lua
osm_rawdata/import/raw_with_ref.lua
osm_rawdata/import/ways_line.sql
osm_rawdata/import/ways_poly.sql
osm_rawdata/importer.py
osm_rawdata/models.py
osm_rawdata/overture.py
osm_rawdata/pgasync.py
osm_rawdata/postgres.py
osm_rawdata-0.4.2.dist-info/entry_points.txt
osm_rawdata-0.4.2.dist-info/WHEEL
osm_rawdata-0.4.2.dist-info/METADATA
osm_rawdata-0.4.2.dist-info/licenses/LICENSE.md
osm_rawdata-0.4.2.dist-info/RECORD
