Metadata-Version: 2.1
Name: osm-rawdata
Version: 0.4.2
Summary: Make data extracts from OSM data.
License: AGPL-3.0-only
Keywords: hot,osm,openstreetmap
Author-email: Rob Savoye <rob.savoye@hotosm.org>,Sam Woodcock <sam.woodcock@hotosm.org>
Requires-Python: >=3.10
Classifier: Programming Language :: Python :: 3
Classifier: Programming Language :: Python :: 3.10
Classifier: Programming Language :: Python :: 3.11
Classifier: Topic :: Scientific/Engineering :: GIS
Classifier: Topic :: Utilities
Requires-Dist: PyYAML>=6.0.0
Requires-Dist: flatdict>=4.0.1
Requires-Dist: geojson>=2.5.0
Requires-Dist: psycopg2>=2.9.1
Requires-Dist: requests>=2.26.0
Requires-Dist: shapely>=1.8.1
Project-URL: documentation, https://hotosm.github.io/osm-rawdata
Project-URL: homepage, https://hotosm.github.io/osm-rawdata
Project-URL: repository, https://github.com/hotosm/osm-rawdata
